{
  "name": "switch",
  "module_path": "components.radix.themes.components.switch",
  "module_name": "switch",
  "file_path": "/Users/dave/code/griffe_reflex/reflex/reflex/components/radix/themes/components/switch.py",
  "doc_path": "/Users/dave/code/griffe_reflex/reflex/docs/library/forms/switch.md",
  "docstring": "A toggle switch alternative to the checkbox.",
  "bases": [
    "RadixThemesComponent"
  ],
  "properties": [
    {
      "name": "as_child",
      "type": "bool",
      "docstring": "Change the default rendered element for the one passed as a child, merging their props and behavior."
    },
    {
      "name": "default_checked",
      "type": "bool",
      "docstring": "Whether the switch is checked by default"
    },
    {
      "name": "checked",
      "type": "bool",
      "docstring": "Whether the switch is checked"
    },
    {
      "name": "disabled",
      "type": "bool",
      "docstring": "If true, prevent the user from interacting with the switch"
    },
    {
      "name": "required",
      "type": "bool",
      "docstring": "If true, the user must interact with the switch to submit the form"
    },
    {
      "name": "name",
      "type": "str",
      "docstring": "The name of the switch (when submitting a form)"
    },
    {
      "name": "value",
      "type": "str",
      "docstring": "The value associated with the \"on\" position"
    },
    {
      "name": "high_contrast",
      "type": "bool",
      "docstring": "Whether to render the switch with higher contrast color against background"
    }
  ],
  "events": [
    {
      "name": "on_change",
      "type": "EventHandler[passthrough_event_spec(bool)",
      "docstring": "Fired when the value of the switch changes"
    }
  ],
  "styling_props": [
    {
      "name": "size",
      "type": "Responsive[LiteralSwitchSize]",
      "docstring": "Switch size \"1\" - \"4\""
    },
    {
      "name": "variant",
      "type": "Literal[\"classic\", \"surface\", \"soft\"]",
      "docstring": "Variant of switch: \"classic\" | \"surface\" | \"soft\""
    },
    {
      "name": "color_scheme",
      "type": "LiteralAccentColor",
      "docstring": "Override theme color for switch"
    },
    {
      "name": "radius",
      "type": "Literal[\"none\", \"small\", \"full\"]",
      "docstring": "Override theme radius for switch: \"none\" | \"small\" | \"full\""
    }
  ]
}